setup.py
django_hierarchical.egg-info/PKG-INFO
django_hierarchical.egg-info/SOURCES.txt
django_hierarchical.egg-info/dependency_links.txt
django_hierarchical.egg-info/top_level.txt
django_hierarchy/__init__.py
django_hierarchy/admin.py
django_hierarchy/forms.py
django_hierarchy/helpers.py
django_hierarchy/managers.py
django_hierarchy/models.py