Metadata-Version: 1.0
Name: django-hierarchical
Version: 0.1.6
Summary: Hierarchical models and form fields for Django
Home-page: http://moxypark.co.uk/
Author: Moxy Park
Author-email: moxypark@me.com
License: UNKNOWN
Platform: UNKNOWN
Classifier: Development Status :: 3 - Alpha
Classifier: Environment :: Web Environment
Classifier: Framework :: Django
Classifier: Intended Audience :: Developers
Classifier: Operating System :: OS Independent
Classifier: Programming Language :: Python
Classifier: Framework :: Django
